Workbook

Sheet Premissas
A1: EVOLUT x BYD — PREMISSAS (PAINEL DE CONTROLE)
A2: Altere os valores em amarelo: toda a planilha recalcula automaticamente.
A3: Premissa | B3: Valor | C3: Unidade | D3: Observacao
A4: Total de concessionarias BYD no Brasil | B4: 220 | C4: unid. | D4: meta: 250 concessionarias
A5: Meta de concessionarias BYD | B5: 250 | C5: unid. | D5: expansao planejada
A6: BEVs vendidos/ano no Brasil (BYD, 2025) | B6: 46000 | C6: unid./ano | D6: lider com 73,62% do mercado BEV
A7: % das vendas BEV concentradas em SP | B7: 0.25 | C7: % | D7: maior concentracao: SP, DF, RJ, RS
A8: Valor mensal SaaS por concessionaria | B8: 800 | C8: R$/mes | D8: linha de receita 1
A9: Valor mensal por totem publico (itinerante) | B9: 1500 | C9: R$/mes | D9: shoppings, aeroportos, eventos
A10: Valor por lead qualificado | B10: 25 | C10: R$/lead | D10: linha de receita 2
A11: Valor da instalacao solar por kit (com imposto) | B11: 2200 | C11: R$/kit | D11: kit: 4 paineis + 1 microinversor (~2,2 kWp)
A12: Carga tributaria embutida na instalacao | B12: 0.15 | C12: % | D12: imposto incluso no valor do kit
A13: Custo repassado ao instalador credenciado por kit | B13: 1500 | C13: R$/kit | D13: repasse ao instalador acreditado
A14: % adesao a instalacao solar — cenario conservador | B14: 0.5 | C14: % | D14: cenario 1 de 3
A15: % adesao a instalacao solar — cenario realista | B15: 0.65 | C15: % | D15: cenario 2 de 3
... A18: Leads gerados por totem por mes | B18: 150 | C18: leads/totem/mes | D18: estimativa para calculo da linha de receita 2
A20: Premissas de custos (DRE)
A21: Custo de infraestrutura/hospedagem do SaaS (% da receita SaaS) | B21: 0.05 | C21: % | D21: servidores, cloud, manutencao de software
A22: Custo de manutencao por totem (R$/totem/mes) | B22: 150 | C22: R$/totem/mes | D22: manutencao fisica e suporte tecnico
A23: Custo de equipe de coordenacao (mensal) | B23: 30000 | C23: R$/mes | D23: equipe interna de operacao e parcerias
A24: Impostos sobre receita de servicos (% da receita bruta) | B24: 0.08 | C24: % | D24: ISS/PIS/COFINS sobre servicos prestados
A25: Marketing e aquisicao (% da receita bruta) | B25: 0.04 | C25: % | D25: campanhas, eventos, materiais
A28: Projecao baseada em dados publicos de mercado (Fenabrave/BYD 2025). Adesao e distribuicao por estado sao estimativas a validar em piloto.

Sheet Concessionarias e Totens
A1: DISTRIBUICAO DE CONCESSIONARIAS E TOTENS POR ESTADO
A3: Estado | B3: % estimado de mercado BYD | C3: Nº de concessionarias (estimado) | D3: Totens em concessionaria | E3: Totens itinerantes (estimado) | F3: Total de totens no estado | G3: Receita SaaS concessionarias/mes (R$) | H3: Receita totens itinerantes/mes (R$)
A4: Sao Paulo | B4: 0.2 | C4: =ROUND(Premissas!$B$4*B4,0) | D4: =C4 | E4: =ROUND(C4/3,0) | F4: =D4+E4 | G4: =C4*Premissas!$B$8 | H4: =E4*Premissas!$B$9
A5: Rio de Janeiro | B5: 0.09 | C5: =ROUND(Premissas!$B$4*B5,0) | D5: =C5 | E5: =ROUND(C5/3,0) | F5: =D5+E5 | G5: =C5*Premissas!$B$8 | H5: =E5*Premissas!$B$9
A6: Minas Gerais | B6: 0.08 | C6: =ROUND(Premissas!$B$4*B6,0) | D6: =C6 | E6: =ROUND(C6/3,0) | F6: =D6+E6 | G6: =C6*Premissas!$B$8 | H6: =E6*Premissas!$B$9
A7: Parana | B7: 0.08 | C7: =ROUND(Premissas!$B$4*B7,0) | D7: =C7 | E7: =ROUND(C7/3,0) | F7: =D7+E7 | G7: =C7*Premissas!$B$8 | H7: =E7*Premissas!$B$9
A8: Rio Grande do Sul | B8: 0.08 | C8: =ROUND(Premissas!$B$4*B8,0) | D8: =C8 | E8: =ROUND(C8/3,0) | F8: =D8+E8 | G8: =C8*Premissas!$B$8 | H8: =E8*Premissas!$B$9
A9: Distrito Federal | B9: 0.06 | C9: =ROUND(Premissas!$B$4*B9,0) | D9: =C9 | E9: =ROUND(C9/3,0) | F9: =D9+E9 | G9: =C9*Premissas!$B$8 | H9: =E9*Premissas!$B$9
A10: Bahia | B10: 0.06 | C10: =ROUND(Premissas!$B$4*B10,0) | D10: =C10 | E10: =ROUND(C10/3,0) | F10: =D10+E10 | G10: =C10*Premissas!$B$8 | H10: =E10*Premissas!$B$9
A11: Santa Catarina | B11: 0.05 | C11: =ROUND(Premissas!$B$4*B11,0) | D11: =C11 | E11: =ROUND(C11/3,0) | F11: =D11+E11 | G11: =C11*Premissas!$B$8 | H11: =E11*Premissas!$B$9
A12: Goias | B12: 0.04 | C12: =ROUND(Premissas!$B$4*B12,0) | D12: =C12 | E12: =ROUND(C12/3,0) | F12: =D12+E12 | G12: =C12*Premissas!$B$8 | H12: =E12*Premissas!$B$9
A13: Pernambuco | B13: 0.04 | C13: =ROUND(Premissas!$B$4*B13,0) | D13: =C13 | E13: =ROUND(C13/3,0) | F13: =D13+E13 | G13: =C13*Premissas!$B$8 | H13: =E13*Premissas!$B$9
A14: Ceara | B14: 0.02 | C14: =ROUND(Premissas!$B$4*B14,0) | D14: =C14 | E14: =ROUND(C14/3,0) | F14: =D14+E14 | G14: =C14*Premissas!$B$8 | H14: =E14*Premissas!$B$9
A15: Espirito Santo | B15: 0.02 | C15: =ROUND(Premissas!$B$4*B15,0) | D15: =C15 | E15: =ROUND(C15/3,0) | F15: =D15+E15 | G15: =C15*Premissas!$B$8 | H15: =E15*Premissas!$B$9
... A30: Amapa | B30: 0.01 | C30: =ROUND(Premissas!$B$4*B30,0) | D30: =C30 | E30: =ROUND(C30/3,0) | F30: =D30+E30 | G30: =C30*Premissas!$B$8 | H30: =E30*Premissas!$B$9
A31: TOTAL | B31: =SUM(B4:B30) | C31: =SUM(C4:C30) | D31: =SUM(D4:D30) | E31: =SUM(E4:E30) | F31: =SUM(F4:F30) | G31: =SUM(G4:G30) | H31: =SUM(H4:H30)
A33: Nota: totens itinerantes circulam por shoppings, aeroportos e eventos de grande fluxo, ampliando a presenca da marca alem das concessionarias fixas.
A35: Projecao baseada em dados publicos de mercado (Fenabrave/BYD 2025). Adesao e distribuicao por estado sao estimativas a validar em piloto.

Sheet Instalacoes Solares (SP)
A1: INSTALACOES SOLARES — VOLUME E RENTABILIDADE (SAO PAULO)
A3: BEVs vendidos/ano no Brasil | B3: =Premissas!$B$6
A4: % das vendas BEV concentradas em SP | B4: =Premissas!$B$7
A5: BEVs vendidos/ano em SP | B5: =B3*B4
A7: Indicador (cenarios de adesao a instalacao solar) | B7: Conservador (50%) | C7: Realista (65%) | D7: Agressivo (75%)
A8: % de adesao a instalacao solar | B8: =Premissas!$B$14 | C8: =Premissas!$B$15 | D8: =Premissas!$B$16
A9: Instalacoes/ano | B9: =ROUND($B$5*B8,0) | C9: =ROUND($B$5*C8,0) | D9: =ROUND($B$5*D8,0)
A10: Instalacoes/mes | B10: =B9/12 | C10: =C9/12 | D10: =D9/12
A11: Receita bruta de instalacao (R$/ano) | B11: =B9*Premissas!$B$11 | C11: =C9*Premissas!$B$11 | D11: =D9*Premissas!$B$11
A12: Imposto embutido na instalacao (R$/ano) | B12: =B9*Premissas!$B$11*Premissas!$B$12 | C12: =C9*Premissas!$B$11*Premissas!$B$12 | D12: =D9*Premissas!$B$11*Premissas!$B$12
A13: Custo repassado ao instalador (R$/ano) | B13: =B9*Premissas!$B$13 | C13: =C9*Premissas!$B$13 | D13: =D9*Premissas!$B$13
A14: Margem liquida por kit (R$) | B14: =Premissas!$B$11-(Premissas!$B$11*Premissas!$B$12)-Premissas!$B$13 | C14: =Premissas!$B$11-(Premissas!$B$11*Premissas!$B$12)-Premissas!$B$13 | D14: =Premissas!$B$11-(Premissas!$B$11*Premissas!$B$12)-Premissas!$B$13
A15: Receita liquida total no cenario (R$/ano) | B15: =B9*B14 | C15: =C9*C14 | D15: =D9*D14
A18: Projecao baseada em dados publicos de mercado (Fenabrave/BYD 2025). Adesao e distribuicao por estado sao estimativas a validar em piloto.

Sheet Receita Consolidada (DRE)
A1: RECEITA CONSOLIDADA — DRE SIMPLIFICADO ANUAL (3 CENARIOS)
A3: Linha | B3: Conservador (adesao 50%) | C3: Realista (adesao 65%) | D3: Agressivo (adesao 75%)
A4: 1. Receita SaaS concessionarias (anual) | B4: ='Concessionarias e Totens'!$C$31*Premissas!$B$8*12 | C4: =$B4 | D4: =$B4
A5: 2. Receita SaaS totens itinerantes (anual) | B5: ='Concessionarias e Totens'!$E$31*Premissas!$B$9*12 | C5: =$B5 | D5: =$B5
A6: 3. Receita por taxa de leads (anual) | B6: ='Concessionarias e Totens'!$F$31*Premissas!$B$18*12*Premissas!$B$10 | C6: =$B6 | D6: =$B6
A7: 4. Margem liquida instalacoes solares (anual) | B7: ='Instalacoes Solares (SP)'!$B$15 | C7: ='Instalacoes Solares (SP)'!$C$15 | D7: ='Instalacoes Solares (SP)'!$D$15
A8: 5. Receita taxa de plataforma de gestao (anual) | B8: =Premissas!$B$17*12 | C8: =$B8 | D8: =$B8
A9: RECEITA BRUTA TOTAL | B9: =SUM(B4:B8) | C9: =SUM(C4:C8) | D9: =SUM(D4:D8)
A11: Custo: infraestrutura/hospedagem SaaS | B11: =Premissas!$B$21*(B4+B5) | C11: =Premissas!$B$21*(C4+C5) | D11: =Premissas!$B$21*(D4+D5)
A12: Custo: manutencao de totens | B12: ='Concessionarias e Totens'!$F$31*Premissas!$B$22*12 | C12: ='Concessionarias e Totens'!$F$31*Premissas!$B$22*12 | D12: ='Concessionarias e Totens'!$F$31*Premissas!$B$22*12
A13: Custo: equipe de coordenacao | B13: =Premissas!$B$23*12 | C13: =Premissas!$B$23*12 | D13: =Premissas!$B$23*12
A14: Custo: impostos sobre receita de servicos | B14: =Premissas!$B$24*B9 | C14: =Premissas!$B$24*C9 | D14: =Premissas!$B$24*D9
A15: Custo: marketing e aquisicao | B15: =Premissas!$B$25*B9 | C15: =Premissas!$B$25*C9 | D15: =Premissas!$B$25*D9
A16: CUSTOS TOTAIS | B16: =SUM(B11:B15) | C16: =SUM(C11:C15) | D16: =SUM(D11:D15)
A18: RESULTADO LIQUIDO ESTIMADO | B18: =B9-B16 | C18: =C9-C16 | D18: =D9-D16
A19: Margem liquida (%) | B19: =B18/B9 | C19: =C18/C9 | D19: =D18/D9
A21: Projecao baseada em dados publicos de mercado (Fenabrave/BYD 2025). Adesao e distribuicao por estado sao estimativas a validar em piloto.

Sheet Resumo Executivo
A1: RESUMO EXECUTIVO — EVOLUT x BYD (CENARIO REALISTA: ADESAO 65%)
A3: Receita bruta total anual | B3: Nº de concessionarias | C3: Nº total de totens | D3: Instalacoes solares/ano | E3: Resultado liquido estimado (anual)
A4: ='Receita Consolidada (DRE)'!$C$9 | B4: ='Concessionarias e Totens'!$C$31 | C4: ='Concessionarias e Totens'!$F$31 | D4: ='Instalacoes Solares (SP)'!$C$9 | E4: ='Receita Consolidada (DRE)'!$C$18
A7: Receita por linha (cenario realista, anual)
A8: Linha de receita | B8: Valor anual (R$)
A9: 1. SaaS concessionarias | B9: ='Receita Consolidada (DRE)'!$C$4
A10: 2. SaaS totens itinerantes | B10: ='Receita Consolidada (DRE)'!$C$5
A11: 3. Taxa por leads | B11: ='Receita Consolidada (DRE)'!$C$6
A12: 4. Margem liquida instalacoes solares | B12: ='Receita Consolidada (DRE)'!$C$7
A13: 5. Taxa de plataforma de gestao | B13: ='Receita Consolidada (DRE)'!$C$8
A16: Comparacao de cenarios — resultado liquido anual
A17: Cenario | B17: Resultado liquido (R$)
A18: Conservador (adesao 50%) | B18: ='Receita Consolidada (DRE)'!$B$18
A19: Realista (adesao 65%) | B19: ='Receita Consolidada (DRE)'!$C$18
A20: Agressivo (adesao 75%) | B20: ='Receita Consolidada (DRE)'!$D$18
A39: Projecao baseada em dados publicos de mercado (Fenabrave/BYD 2025). Adesao e distribuicao por estado sao estimativas a validar em piloto.
